{
  "division": "08",
  "title": { "en": "Timber, Carpentry & Composites" },
  "sections": [
    { "key": "08.00", "title": { "en": "Timber and carpentry — general" } },
    { "key": "08.01", "title": { "en": "Structural timber framing and carpentry" } },
    { "key": "08.02", "title": { "en": "Engineered timber — glulam and CLT" } },
    { "key": "08.03", "title": { "en": "Roof trusses and prefabricated frames" } },
    { "key": "08.04", "title": { "en": "First-fix carpentry and floor joists" } },
    { "key": "08.05", "title": { "en": "Sheathing, boarding and structural panels" } },
    { "key": "08.06", "title": { "en": "Second-fix carpentry and timber trim" } },
    { "key": "08.07", "title": { "en": "Timber treatment and preservation" } },
    { "key": "08.08", "title": { "en": "Composite and fibre-reinforced structural members" } },
    { "key": "08.09", "title": { "en": "Other timber and composite work" } }
  ]
}
