{
  "division": "27",
  "title": { "en": "Utilities & Infrastructure" },
  "sections": [
    { "key": "27.00", "title": { "en": "Utilities and infrastructure — general" } },
    { "key": "27.01", "title": { "en": "Potable water mains and distribution" } },
    { "key": "27.02", "title": { "en": "Foul and sanitary sewer mains" } },
    { "key": "27.03", "title": { "en": "Storm sewers and surface-water networks" } },
    { "key": "27.04", "title": { "en": "Gas mains and distribution networks" } },
    { "key": "27.05", "title": { "en": "District heating and cooling networks" } },
    { "key": "27.06", "title": { "en": "Electrical distribution and substations (utility)" } },
    { "key": "27.07", "title": { "en": "Telecoms and fibre ducting networks" } },
    { "key": "27.08", "title": { "en": "Pumping stations and lift stations" } },
    { "key": "27.09", "title": { "en": "Trenchless works — directional drilling and microtunnelling" } },
    { "key": "27.10", "title": { "en": "Manholes, chambers and utility structures" } },
    { "key": "27.11", "title": { "en": "Other utilities and infrastructure" } }
  ]
}
